BradleysStrings/BradleysStrings.py
BradleysStrings/__init__.py
bradleysstrings-0.0.1.dist-info/METADATA
bradleysstrings-0.0.1.dist-info/WHEEL
bradleysstrings-0.0.1.dist-info/licenses/LICENSE
bradleysstrings-0.0.1.dist-info/RECORD
