Metadata-Version: 2.4
Name: BradleysStrings
Version: 0.0.1
Summary: Morer stuff for dealing with strings!
Project-URL: Homepage, https://github.com/bradley-dev777/BradleysStrings-python/
Project-URL: Issues, https://github.com/bradley-dev777/BradleysStrings-python/issues
Author-email: Bradley Hu <bradleyhu0707@gmail.com>, Jayden Yin <technodragon555@gmail.com>
License-Expression: GPL-3.0
License-File: LICENSE
Classifier: Operating System :: OS Independent
Classifier: Programming Language :: Python
Requires-Python: >=3.9
